design.v

module spi_master (
    input        clk,
    input        rst,
    input        start,
    input  [1:0] mode,      // {CPOL, CPHA}
    input  [7:0] data_in,
    output reg   mosi,
    output reg   sclk,
    output reg   cs,
    output reg   done
);

wire cpol = mode[1];
wire cpha = mode[0];

reg [3:0] bit_cnt;
reg [7:0] shift_reg;
reg [3:0] clk_div;
reg       busy;

wire sclk_en = (clk_div == 4);
wire leading_edge  = sclk_en && busy && (sclk ==  cpol);
wire trailing_edge = sclk_en && busy && (sclk == ~cpol);

always @(posedge clk or posedge rst) begin
    if (rst) begin
        mosi      <= 0;
        sclk      <= 0;
        cs        <= 1;
        done      <= 0;
        bit_cnt   <= 0;
        shift_reg <= 0;
        clk_div   <= 0;
        busy      <= 0;
    end else begin
        done <= 0;

        if (start && !busy) begin
            busy      <= 1;
            cs        <= 0;
            shift_reg <= data_in;
            bit_cnt   <= 0;
            clk_div   <= 0;
            sclk      <= cpol;     

            // CPHA=0: Truyền bit đầu tiên ngay khi CS xuống
            if (!cpha)
                mosi <= data_in[7];
        end

        if (busy) begin
            clk_div <= clk_div + 1;

            if (sclk_en) begin
                clk_div <= 0;
                sclk    <= ~sclk;
            end

            // MODE 0 & MODE 2
            if (!cpha && trailing_edge) begin
                if (bit_cnt == 8) begin
                    busy <= 0;
                    cs   <= 1;
                    done <= 1;
                end else begin
                    shift_reg <= {shift_reg[6:0], 1'b0};
                    mosi      <= shift_reg[6];
                end
                bit_cnt <= bit_cnt + 1;
            end

            // MODE 1 & MODE 3
            if (cpha && leading_edge) begin
                mosi      <= shift_reg[7];
                shift_reg <= {shift_reg[6:0], 1'b0};
                if (bit_cnt == 8) begin
                    busy <= 0;
                    cs   <= 1;
                    done <= 1;
                end
                bit_cnt <= bit_cnt + 1;
            end
        end

    end
end

endmodule

testbench.v
`timescale 1ns / 1ps
`include "design.v"

module spi_master_tb;
    reg        clk;
    reg        rst;
    reg        start;
    reg  [1:0] mode;
    reg  [7:0] data_in;

    wire       mosi;
    wire       sclk;
    wire       cs;
    wire       done;

    spi_master uut ( .clk(clk), .rst(rst), .start(start), .mode(mode), .data_in(data_in), .mosi(mosi), .sclk(sclk), .cs(cs), .done(done));

    initial clk = 0;
    always #5 clk = ~clk;

    initial begin
        $dumpfile("design.vcd");
        $dumpvars(0, spi_master_tb);

        rst     = 1; // Reset
        start   = 0;
        mode    = 2'b00;
        data_in = 8'h00;
        #40;
        rst = 0;      
        #40;

        //Mode 0 (CPOL=0, CPHA=0)
        mode    = 2'b00;
        data_in = 8'hA5;
        #40;
        start = 1; #10; start = 0;
        #1000;

        //Mode 1 (CPOL=0, CPHA=1)
        mode    = 2'b01;
        data_in = 8'h3C;
        #40;
        start = 1; #10; start = 0;
        #1000;

        //Mode 2 (CPOL=1, CPHA=0)
        mode    = 2'b10;
        data_in = 8'h69;
        #40;
        start = 1; #10; start = 0;
        #1000;

        //Mode 3 (CPOL=1, CPHA=1)
        mode    = 2'b11;
        data_in = 8'hF0;
        #40;
        start = 1; #10; start = 0;
        #1000;

        $finish;
    end

endmodule

SPI-4-MODE-Simulation/design.vcd
$date
   Wed Jun 24 17:58:52 2026
$end
$version
  P.20131013
$end
$timescale
  1ps
$end
$scope module spi_master_tb $end
$var wire 1 ! mosi $end
$var wire 1 " sclk $end
$var wire 1 # cs $end
$var wire 1 $ done $end
$var reg 1 % clk $end
$var reg 1 & rst $end
$var reg 1 ' start $end
$var reg 2 ( mode [1:0] $end
$var reg 8 ) data_in [7:0] $end
$scope module uut $end
$var wire 1 * clk $end
$var wire 1 + rst $end
$var wire 1 , start $end
$var wire 1 - mode [1] $end
$var wire 1 . mode [0] $end
$var wire 1 / data_in [7] $end
$var wire 1 0 data_in [6] $end
$var wire 1 1 data_in [5] $end
$var wire 1 2 data_in [4] $end
$var wire 1 3 data_in [3] $end
$var wire 1 4 data_in [2] $end
$var wire 1 5 data_in [1] $end
$var wire 1 6 data_in [0] $end
$var wire 1 7 cpol $end
$var wire 1 8 cpha $end
$var wire 1 9 sclk_en $end
$var wire 1 : leading_edge $end
$var wire 1 ; trailing_edge $end
$var reg 1 < mosi $end
$var reg 1 = sclk $end
$var reg 1 > cs $end
$var reg 1 ? done $end
$var reg 4 @ bit_cnt [3:0] $end
$var reg 8 A shift_reg [7:0] $end
$var reg 4 B clk_div [3:0] $end
$var reg 1 C busy $end
$upscope $end
$upscope $end
$enddefinitions $end
#0
$dumpvars
1+
0,
0.
0*
0!
0"
1#
0$
0-
06
05
04
03
02
01
00
0/
0%
1&
0'
b0 (
b0 )
0<
0=
1>
0?
b0 @
b0 A
b0 B
0C
07
08
09
0:
0;
$end
#5000
1*
1%
#10000
0*
0%
#15000
1*
1%
#20000
0*
0%
#25000
1*
1%
#30000
0*
0%
#35000
1*
1%
#40000
0+
0*
0%
0&
#45000
1*
1%
#50000
0*
0%
#55000
1*
1%
#60000
0*
0%
#65000
1*
1%
#70000
0*
0%
#75000
1*
1%
#80000
0*
16
14
11
1/
0%
b10100101 )
#85000
1*
1%
#90000
0*
0%
#95000
1*
1%
#100000
0*
0%
#105000
1*
1%
#110000
0*
0%
#115000
1*
1%
#120000
1,
0*
0%
1'
#125000
1*
1!
0#
1%
1<
0>
b10100101 A
1C
#130000
0,
0*
0%
0'
#135000
1*
1%
b1 B
#140000
0*
0%
#145000
1*
1%
b10 B
#150000
0*
0%
#155000
1*
1%
b11 B
#160000
0*
0%
#165000
1*
1%
b100 B
19
1:
#170000
0*
0%
#175000
1*
1"
1%
1=
b0 B
09
0:
#180000
0*
0%
#185000
1*
1%
b1 B
#190000
0*
0%
#195000
1*
1%
b10 B
#200000
0*
0%
#205000
1*
1%
b11 B
#210000
0*
0%
#215000
1*
1%
b100 B
19
1;
#220000
0*
0%
#225000
1*
0!
0"
1%
0<
0=
b1 @
b1001010 A
b0 B
09
0;
#230000
0*
0%
#235000
1*
1%
b1 B
#240000
0*
0%
#245000
1*
1%
b10 B
#250000
0*
0%
#255000
1*
1%
b11 B
#260000
0*
0%
#265000
1*
1%
b100 B
19
1:
#270000
0*
0%
#275000
1*
1"
1%
1=
b0 B
09
0:
#280000
0*
0%
#285000
1*
1%
b1 B
#290000
0*
0%
#295000
1*
1%
b10 B
#300000
0*
0%
#305000
1*
1%
b11 B
#310000
0*
0%
#315000
1*
1%
b100 B
19
1;
#320000
0*
0%
#325000
1*
1!
0"
1%
1<
0=
b10 @
b10010100 A
b0 B
09
0;
#330000
0*
0%
#335000
1*
1%
b1 B
#340000
0*
0%
#345000
1*
1%
b10 B
#350000
0*
0%
#355000
1*
1%
b11 B
#360000
0*
0%
#365000
1*
1%
b100 B
19
1:
#370000
0*
0%
#375000
1*
1"
1%
1=
b0 B
09
0:
#380000
0*
0%
#385000
1*
1%
b1 B
#390000
0*
0%
#395000
1*
1%
b10 B
#400000
0*
0%
#405000
1*
1%
b11 B
#410000
0*
0%
#415000
1*
1%
b100 B
19
1;
#420000
0*
0%
#425000
1*
0!
0"
1%
0<
0=
b11 @
b101000 A
b0 B
09
0;
#430000
0*
0%
#435000
1*
1%
b1 B
#440000
0*
0%
#445000
1*
1%
b10 B
#450000
0*
0%
#455000
1*
1%
b11 B
#460000
0*
0%
#465000
1*
1%
b100 B
19
1:
#470000
0*
0%
#475000
1*
1"
1%
1=
b0 B
09
0:
#480000
0*
0%
#485000
1*
1%
b1 B
#490000
0*
0%
#495000
1*
1%
b10 B
#500000
0*
0%
#505000
1*
1%
b11 B
#510000
0*
0%
#515000
1*
1%
b100 B
19
1;
#520000
0*
0%
#525000
1*
0"
1%
0=
b100 @
b1010000 A
b0 B
09
0;
#530000
0*
0%
#535000
1*
1%
b1 B
#540000
0*
0%
#545000
1*
1%
b10 B
#550000
0*
0%
#555000
1*
1%
b11 B
#560000
0*
0%
#565000
1*
1%
b100 B
19
1:
#570000
0*
0%
#575000
1*
1"
1%
1=
b0 B
09
0:
#580000
0*
0%
#585000
1*
1%
b1 B
#590000
0*
0%
#595000
1*
1%
b10 B
#600000
0*
0%
#605000
1*
1%
b11 B
#610000
0*
0%
#615000
1*
1%
b100 B
19
1;
#620000
0*
0%
#625000
1*
1!
0"
1%
1<
0=
b101 @
b10100000 A
b0 B
09
0;
#630000
0*
0%
#635000
1*
1%
b1 B
#640000
0*
0%
#645000
1*
1%
b10 B
#650000
0*
0%
#655000
1*
1%
b11 B
#660000
0*
0%
#665000
1*
1%
b100 B
19
1:
#670000
0*
0%
#675000
1*
1"
1%
1=
b0 B
09
0:
#680000
0*
0%
#685000
1*
1%
b1 B
#690000
0*
0%
#695000
1*
1%
b10 B
#700000
0*
0%
#705000
1*
1%
b11 B
#710000
0*
0%
#715000
1*
1%
b100 B
19
1;
#720000
0*
0%
#725000
1*
0!
0"
1%
0<
0=
b110 @
b1000000 A
b0 B
09
0;
#730000
0*
0%
#735000
1*
1%
b1 B
#740000
0*
0%
#745000
1*
1%
b10 B
#750000
0*
0%
#755000
1*
1%
b11 B
#760000
0*
0%
#765000
1*
1%
b100 B
19
1:
#770000
0*
0%
#775000
1*
1"
1%
1=
b0 B
09
0:
#780000
0*
0%
#785000
1*
1%
b1 B
#790000
0*
0%
#795000
1*
1%
b10 B
#800000
0*
0%
#805000
1*
1%
b11 B
#810000
0*
0%
#815000
1*
1%
b100 B
19
1;
#820000
0*
0%
#825000
1*
1!
0"
1%
1<
0=
b111 @
b10000000 A
b0 B
09
0;
#830000
0*
0%
#835000
1*
1%
b1 B
#840000
0*
0%
#845000
1*
1%
b10 B
#850000
0*
0%
#855000
1*
1%
b11 B
#860000
0*
0%
#865000
1*
1%
b100 B
19
1:
#870000
0*
0%
#875000
1*
1"
1%
1=
b0 B
09
0:
#880000
0*
0%
#885000
1*
1%
b1 B
#890000
0*
0%
#895000
1*
1%
b10 B
#900000
0*
0%
#905000
1*
1%
b11 B
#910000
0*
0%
#915000
1*
1%
b100 B
19
1;
#920000
0*
0%
#925000
1*
0!
0"
1%
0<
0=
b1000 @
b0 A
b0 B
09
0;
#930000
0*
0%
#935000
1*
1%
b1 B
#940000
0*
0%
#945000
1*
1%
b10 B
#950000
0*
0%
#955000
1*
1%
b11 B
#960000
0*
0%
#965000
1*
1%
b100 B
19
1:
#970000
0*
0%
#975000
1*
1"
1%
1=
b0 B
09
0:
#980000
0*
0%
#985000
1*
1%
b1 B
#990000
0*
0%
#995000
1*
1%
b10 B
#1000000
0*
0%
#1005000
1*
1%
b11 B
#1010000
0*
0%
#1015000
1*
1%
b100 B
19
1;
#1020000
0*
0%
#1025000
1*
0"
1#
1$
1%
0=
1>
1?
b1001 @
b0 B
0C
09
0;
#1030000
0*
0%
#1035000
1*
0$
1%
0?
#1040000
0*
0%
#1045000
1*
1%
#1050000
0*
0%
#1055000
1*
1%
#1060000
0*
0%
#1065000
1*
1%
#1070000
0*
0%
#1075000
1*
1%
#1080000
0*
0%
#1085000
1*
1%
#1090000
0*
0%
#1095000
1*
1%
#1100000
0*
0%
#1105000
1*
1%
#1110000
0*
0%
#1115000
1*
1%
#1120000
0*
0%
#1125000
1*
1%
#1130000
1.
0*
06
13
12
0/
0%
b1 (
b111100 )
18
#1135000
1*
1%
#1140000
0*
0%
#1145000
1*
1%
#1150000
0*
0%
#1155000
1*
1%
#1160000
0*
0%
#1165000
1*
1%
#1170000
1,
0*
0%
1'
#1175000
1*
0#
1%
0>
b0 @
b111100 A
1C
#1180000
0,
0*
0%
0'
#1185000
1*
1%
b1 B
#1190000
0*
0%
#1195000
1*
1%
b10 B
#1200000
0*
0%
#1205000
1*
1%
b11 B
#1210000
0*
0%
#1215000
1*
1%
b100 B
19
1:
#1220000
0*
0%
#1225000
1*
1"
1%
1=
b1 @
b1111000 A
b0 B
09
0:
#1230000
0*
0%
#1235000
1*
1%
b1 B
#1240000
0*
0%
#1245000
1*
1%
b10 B
#1250000
0*
0%
#1255000
1*
1%
b11 B
#1260000
0*
0%
#1265000
1*
1%
b100 B
19
1;
#1270000
0*
0%
#1275000
1*
0"
1%
0=
b0 B
09
0;
#1280000
0*
0%
#1285000
1*
1%
b1 B
#1290000
0*
0%
#1295000
1*
1%
b10 B
#1300000
0*
0%
#1305000
1*
1%
b11 B
#1310000
0*
0%
#1315000
1*
1%
b100 B
19
1:
#1320000
0*
0%
#1325000
1*
1"
1%
1=
b10 @
b11110000 A
b0 B
09
0:
#1330000
0*
0%
#1335000
1*
1%
b1 B
#1340000
0*
0%
#1345000
1*
1%
b10 B
#1350000
0*
0%
#1355000
1*
1%
b11 B
#1360000
0*
0%
#1365000
1*
1%
b100 B
19
1;
#1370000
0*
0%
#1375000
1*
0"
1%
0=
b0 B
09
0;
#1380000
0*
0%
#1385000
1*
1%
b1 B
#1390000
0*
0%
#1395000
1*
1%
b10 B
#1400000
0*
0%
#1405000
1*
1%
b11 B
#1410000
0*
0%
#1415000
1*
1%
b100 B
19
1:
#1420000
0*
0%
#1425000
1*
1!
1"
1%
1<
1=
b11 @
b11100000 A
b0 B
09
0:
#1430000
0*
0%
#1435000
1*
1%
b1 B
#1440000
0*
0%
#1445000
1*
1%
b10 B
#1450000
0*
0%
#1455000
1*
1%
b11 B
#1460000
0*
0%
#1465000
1*
1%
b100 B
19
1;
#1470000
0*
0%
#1475000
1*
0"
1%
0=
b0 B
09
0;
#1480000
0*
0%
#1485000
1*
1%
b1 B
#1490000
0*
0%
#1495000
1*
1%
b10 B
#1500000
0*
0%
#1505000
1*
1%
b11 B
#1510000
0*
0%
#1515000
1*
1%
b100 B
19
1:
#1520000
0*
0%
#1525000
1*
1"
1%
1=
b100 @
b11000000 A
b0 B
09
0:
#1530000
0*
0%
#1535000
1*
1%
b1 B
#1540000
0*
0%
#1545000
1*
1%
b10 B
#1550000
0*
0%
#1555000
1*
1%
b11 B
#1560000
0*
0%
#1565000
1*
1%
b100 B
19
1;
#1570000
0*
0%
#1575000
1*
0"
1%
0=
b0 B
09
0;
#1580000
0*
0%
#1585000
1*
1%
b1 B
#1590000
0*
0%
#1595000
1*
1%
b10 B
#1600000
0*
0%
#1605000
1*
1%
b11 B
#1610000
0*
0%
#1615000
1*
1%
b100 B
19
1:
#1620000
0*
0%
#1625000
1*
1"
1%
1=
b101 @
b10000000 A
b0 B
09
0:
#1630000
0*
0%
#1635000
1*
1%
b1 B
#1640000
0*
0%
#1645000
1*
1%
b10 B
#1650000
0*
0%
#1655000
1*
1%
b11 B
#1660000
0*
0%
#1665000
1*
1%
b100 B
19
1;
#1670000
0*
0%
#1675000
1*
0"
1%
0=
b0 B
09
0;
#1680000
0*
0%
#1685000
1*
1%
b1 B
#1690000
0*
0%
#1695000
1*
1%
b10 B
#1700000
0*
0%
#1705000
1*
1%
b11 B
#1710000
0*
0%
#1715000
1*
1%
b100 B
19
1:
#1720000
0*
0%
#1725000
1*
1"
1%
1=
b110 @
b0 A
b0 B
09
0:
#1730000
0*
0%
#1735000
1*
1%
b1 B
#1740000
0*
0%
#1745000
1*
1%
b10 B
#1750000
0*
0%
#1755000
1*
1%
b11 B
#1760000
0*
0%
#1765000
1*
1%
b100 B
19
1;
#1770000
0*
0%
#1775000
1*
0"
1%
0=
b0 B
09
0;
#1780000
0*
0%
#1785000
1*
1%
b1 B
#1790000
0*
0%
#1795000
1*
1%
b10 B
#1800000
0*
0%
#1805000
1*
1%
b11 B
#1810000
0*
0%
#1815000
1*
1%
b100 B
19
1:
#1820000
0*
0%
#1825000
1*
0!
1"
1%
0<
1=
b111 @
b0 B
09
0:
#1830000
0*
0%
#1835000
1*
1%
b1 B
#1840000
0*
0%
#1845000
1*
1%
b10 B
#1850000
0*
0%
#1855000
1*
1%
b11 B
#1860000
0*
0%
#1865000
1*
1%
b100 B
19
1;
#1870000
0*
0%
#1875000
1*
0"
1%
0=
b0 B
09
0;
#1880000
0*
0%
#1885000
1*
1%
b1 B
#1890000
0*
0%
#1895000
1*
1%
b10 B
#1900000
0*
0%
#1905000
1*
1%
b11 B
#1910000
0*
0%
#1915000
1*
1%
b100 B
19
1:
#1920000
0*
0%
#1925000
1*
1"
1%
1=
b1000 @
b0 B
09
0:
#1930000
0*
0%
#1935000
1*
1%
b1 B
#1940000
0*
0%
#1945000
1*
1%
b10 B
#1950000
0*
0%
#1955000
1*
1%
b11 B
#1960000
0*
0%
#1965000
1*
1%
b100 B
19
1;
#1970000
0*
0%
#1975000
1*
0"
1%
0=
b0 B
09
0;
#1980000
0*
0%
#1985000
1*
1%
b1 B
#1990000
0*
0%
#1995000
1*
1%
b10 B
#2000000
0*
0%
#2005000
1*
1%
b11 B
#2010000
0*
0%
#2015000
1*
1%
b100 B
19
1:
#2020000
0*
0%
#2025000
1*
1"
1#
1$
1%
1=
1>
1?
b1001 @
b0 B
0C
09
0:
#2030000
0*
0%
#2035000
1*
0$
1%
0?
#2040000
0*
0%
#2045000
1*
1%
#2050000
0*
0%
#2055000
1*
1%
#2060000
0*
0%
#2065000
1*
1%
#2070000
0*
0%
#2075000
1*
1%
#2080000
0*
0%
#2085000
1*
1%
#2090000
0*
0%
#2095000
1*
1%
#2100000
0*
0%
#2105000
1*
1%
#2110000
0*
0%
#2115000
1*
1%
#2120000
0*
0%
#2125000
1*
1%
#2130000
0*
0%
#2135000
1*
1%
#2140000
0*
0%
#2145000
1*
1%
#2150000
0*
0%
#2155000
1*
1%
#2160000
0*
0%
#2165000
1*
1%
#2170000
0*
0%
#2175000
1*
1%
#2180000
0.
0*
1-
16
04
02
10
0%
b10 (
b1101001 )
17
08
#2185000
1*
1%
#2190000
0*
0%
#2195000
1*
1%
#2200000
0*
0%
#2205000
1*
1%
#2210000
0*
0%
#2215000
1*
1%
#2220000
1,
0*
0%
1'
#2225000
1*
0#
1%
0>
b0 @
b1101001 A
1C
#2230000
0,
0*
0%
0'
#2235000
1*
1%
b1 B
#2240000
0*
0%
#2245000
1*
1%
b10 B
#2250000
0*
0%
#2255000
1*
1%
b11 B
#2260000
0*
0%
#2265000
1*
1%
b100 B
19
1:
#2270000
0*
0%
#2275000
1*
0"
1%
0=
b0 B
09
0:
#2280000
0*
0%
#2285000
1*
1%
b1 B
#2290000
0*
0%
#2295000
1*
1%
b10 B
#2300000
0*
0%
#2305000
1*
1%
b11 B
#2310000
0*
0%
#2315000
1*
1%
b100 B
19
1;
#2320000
0*
0%
#2325000
1*
1!
1"
1%
1<
1=
b1 @
b11010010 A
b0 B
09
0;
#2330000
0*
0%
#2335000
1*
1%
b1 B
#2340000
0*
0%
#2345000
1*
1%
b10 B
#2350000
0*
0%
#2355000
1*
1%
b11 B
#2360000
0*
0%
#2365000
1*
1%
b100 B
19
1:
#2370000
0*
0%
#2375000
1*
0"
1%
0=
b0 B
09
0:
#2380000
0*
0%
#2385000
1*
1%
b1 B
#2390000
0*
0%
#2395000
1*
1%
b10 B
#2400000
0*
0%
#2405000
1*
1%
b11 B
#2410000
0*
0%
#2415000
1*
1%
b100 B
19
1;
#2420000
0*
0%
#2425000
1*
1"
1%
1=
b10 @
b10100100 A
b0 B
09
0;
#2430000
0*
0%
#2435000
1*
1%
b1 B
#2440000
0*
0%
#2445000
1*
1%
b10 B
#2450000
0*
0%
#2455000
1*
1%
b11 B
#2460000
0*
0%
#2465000
1*
1%
b100 B
19
1:
#2470000
0*
0%
#2475000
1*
0"
1%
0=
b0 B
09
0:
#2480000
0*
0%
#2485000
1*
1%
b1 B
#2490000
0*
0%
#2495000
1*
1%
b10 B
#2500000
0*
0%
#2505000
1*
1%
b11 B
#2510000
0*
0%
#2515000
1*
1%
b100 B
19
1;
#2520000
0*
0%
#2525000
1*
0!
1"
1%
0<
1=
b11 @
b1001000 A
b0 B
09
0;
#2530000
0*
0%
#2535000
1*
1%
b1 B
#2540000
0*
0%
#2545000
1*
1%
b10 B
#2550000
0*
0%
#2555000
1*
1%
b11 B
#2560000
0*
0%
#2565000
1*
1%
b100 B
19
1:
#2570000
0*
0%
#2575000
1*
0"
1%
0=
b0 B
09
0:
#2580000
0*
0%
#2585000
1*
1%
b1 B
#2590000
0*
0%
#2595000
1*
1%
b10 B
#2600000
0*
0%
#2605000
1*
1%
b11 B
#2610000
0*
0%
#2615000
1*
1%
b100 B
19
1;
#2620000
0*
0%
#2625000
1*
1!
1"
1%
1<
1=
b100 @
b10010000 A
b0 B
09
0;
#2630000
0*
0%
#2635000
1*
1%
b1 B
#2640000
0*
0%
#2645000
1*
1%
b10 B
#2650000
0*
0%
#2655000
1*
1%
b11 B
#2660000
0*
0%
#2665000
1*
1%
b100 B
19
1:
#2670000
0*
0%
#2675000
1*
0"
1%
0=
b0 B
09
0:
#2680000
0*
0%
#2685000
1*
1%
b1 B
#2690000
0*
0%
#2695000
1*
1%
b10 B
#2700000
0*
0%
#2705000
1*
1%
b11 B
#2710000
0*
0%
#2715000
1*
1%
b100 B
19
1;
#2720000
0*
0%
#2725000
1*
0!
1"
1%
0<
1=
b101 @
b100000 A
b0 B
09
0;
#2730000
0*
0%
#2735000
1*
1%
b1 B
#2740000
0*
0%
#2745000
1*
1%
b10 B
#2750000
0*
0%
#2755000
1*
1%
b11 B
#2760000
0*
0%
#2765000
1*
1%
b100 B
19
1:
#2770000
0*
0%
#2775000
1*
0"
1%
0=
b0 B
09
0:
#2780000
0*
0%
#2785000
1*
1%
b1 B
#2790000
0*
0%
#2795000
1*
1%
b10 B
#2800000
0*
0%
#2805000
1*
1%
b11 B
#2810000
0*
0%
#2815000
1*
1%
b100 B
19
1;
#2820000
0*
0%
#2825000
1*
1"
1%
1=
b110 @
b1000000 A
b0 B
09
0;
#2830000
0*
0%
#2835000
1*
1%
b1 B
#2840000
0*
0%
#2845000
1*
1%
b10 B
#2850000
0*
0%
#2855000
1*
1%
b11 B
#2860000
0*
0%
#2865000
1*
1%
b100 B
19
1:
#2870000
0*
0%
#2875000
1*
0"
1%
0=
b0 B
09
0:
#2880000
0*
0%
#2885000
1*
1%
b1 B
#2890000
0*
0%
#2895000
1*
1%
b10 B
#2900000
0*
0%
#2905000
1*
1%
b11 B
#2910000
0*
0%
#2915000
1*
1%
b100 B
19
1;
#2920000
0*
0%
#2925000
1*
1!
1"
1%
1<
1=
b111 @
b10000000 A
b0 B
09
0;
#2930000
0*
0%
#2935000
1*
1%
b1 B
#2940000
0*
0%
#2945000
1*
1%
b10 B
#2950000
0*
0%
#2955000
1*
1%
b11 B
#2960000
0*
0%
#2965000
1*
1%
b100 B
19
1:
#2970000
0*
0%
#2975000
1*
0"
1%
0=
b0 B
09
0:
#2980000
0*
0%
#2985000
1*
1%
b1 B
#2990000
0*
0%
#2995000
1*
1%
b10 B
#3000000
0*
0%
#3005000
1*
1%
b11 B
#3010000
0*
0%
#3015000
1*
1%
b100 B
19
1;
#3020000
0*
0%
#3025000
1*
0!
1"
1%
0<
1=
b1000 @
b0 A
b0 B
09
0;
#3030000
0*
0%
#3035000
1*
1%
b1 B
#3040000
0*
0%
#3045000
1*
1%
b10 B
#3050000
0*
0%
#3055000
1*
1%
b11 B
#3060000
0*
0%
#3065000
1*
1%
b100 B
19
1:
#3070000
0*
0%
#3075000
1*
0"
1%
0=
b0 B
09
0:
#3080000
0*
0%
#3085000
1*
1%
b1 B
#3090000
0*
0%
#3095000
1*
1%
b10 B
#3100000
0*
0%
#3105000
1*
1%
b11 B
#3110000
0*
0%
#3115000
1*
1%
b100 B
19
1;
#3120000
0*
0%
#3125000
1*
1"
1#
1$
1%
1=
1>
1?
b1001 @
b0 B
0C
09
0;
#3130000
0*
0%
#3135000
1*
0$
1%
0?
#3140000
0*
0%
#3145000
1*
1%
#3150000
0*
0%
#3155000
1*
1%
#3160000
0*
0%
#3165000
1*
1%
#3170000
0*
0%
#3175000
1*
1%
#3180000
0*
0%
#3185000
1*
1%
#3190000
0*
0%
#3195000
1*
1%
#3200000
0*
0%
#3205000
1*
1%
#3210000
0*
0%
#3215000
1*
1%
#3220000
0*
0%
#3225000
1*
1%
#3230000
1.
0*
06
03
12
1/
0%
b11 (
b11110000 )
18
#3235000
1*
1%
#3240000
0*
0%
#3245000
1*
1%
#3250000
0*
0%
#3255000
1*
1%
#3260000
0*
0%
#3265000
1*
1%
#3270000
1,
0*
0%
1'
#3275000
1*
0#
1%
0>
b0 @
b11110000 A
1C
#3280000
0,
0*
0%
0'
#3285000
1*
1%
b1 B
#3290000
0*
0%
#3295000
1*
1%
b10 B
#3300000
0*
0%
#3305000
1*
1%
b11 B
#3310000
0*
0%
#3315000
1*
1%
b100 B
19
1:
#3320000
0*
0%
#3325000
1*
1!
0"
1%
1<
0=
b1 @
b11100000 A
b0 B
09
0:
#3330000
0*
0%
#3335000
1*
1%
b1 B
#3340000
0*
0%
#3345000
1*
1%
b10 B
#3350000
0*
0%
#3355000
1*
1%
b11 B
#3360000
0*
0%
#3365000
1*
1%
b100 B
19
1;
#3370000
0*
0%
#3375000
1*
1"
1%
1=
b0 B
09
0;
#3380000
0*
0%
#3385000
1*
1%
b1 B
#3390000
0*
0%
#3395000
1*
1%
b10 B
#3400000
0*
0%
#3405000
1*
1%
b11 B
#3410000
0*
0%
#3415000
1*
1%
b100 B
19
1:
#3420000
0*
0%
#3425000
1*
0"
1%
0=
b10 @
b11000000 A
b0 B
09
0:
#3430000
0*
0%
#3435000
1*
1%
b1 B
#3440000
0*
0%
#3445000
1*
1%
b10 B
#3450000
0*
0%
#3455000
1*
1%
b11 B
#3460000
0*
0%
#3465000
1*
1%
b100 B
19
1;
#3470000
0*
0%
#3475000
1*
1"
1%
1=
b0 B
09
0;
#3480000
0*
0%
#3485000
1*
1%
b1 B
#3490000
0*
0%
#3495000
1*
1%
b10 B
#3500000
0*
0%
#3505000
1*
1%
b11 B
#3510000
0*
0%
#3515000
1*
1%
b100 B
19
1:
#3520000
0*
0%
#3525000
1*
0"
1%
0=
b11 @
b10000000 A
b0 B
09
0:
#3530000
0*
0%
#3535000
1*
1%
b1 B
#3540000
0*
0%
#3545000
1*
1%
b10 B
#3550000
0*
0%
#3555000
1*
1%
b11 B
#3560000
0*
0%
#3565000
1*
1%
b100 B
19
1;
#3570000
0*
0%
#3575000
1*
1"
1%
1=
b0 B
09
0;
#3580000
0*
0%
#3585000
1*
1%
b1 B
#3590000
0*
0%
#3595000
1*
1%
b10 B
#3600000
0*
0%
#3605000
1*
1%
b11 B
#3610000
0*
0%
#3615000
1*
1%
b100 B
19
1:
#3620000
0*
0%
#3625000
1*
0"
1%
0=
b100 @
b0 A
b0 B
09
0:
#3630000
0*
0%
#3635000
1*
1%
b1 B
#3640000
0*
0%
#3645000
1*
1%
b10 B
#3650000
0*
0%
#3655000
1*
1%
b11 B
#3660000
0*
0%
#3665000
1*
1%
b100 B
19
1;
#3670000
0*
0%
#3675000
1*
1"
1%
1=
b0 B
09
0;
#3680000
0*
0%
#3685000
1*
1%
b1 B
#3690000
0*
0%
#3695000
1*
1%
b10 B
#3700000
0*
0%
#3705000
1*
1%
b11 B
#3710000
0*
0%
#3715000
1*
1%
b100 B
19
1:
#3720000
0*
0%
#3725000
1*
0!
0"
1%
0<
0=
b101 @
b0 B
09
0:
#3730000
0*
0%
#3735000
1*
1%
b1 B
#3740000
0*
0%
#3745000
1*
1%
b10 B
#3750000
0*
0%
#3755000
1*
1%
b11 B
#3760000
0*
0%
#3765000
1*
1%
b100 B
19
1;
#3770000
0*
0%
#3775000
1*
1"
1%
1=
b0 B
09
0;
#3780000
0*
0%
#3785000
1*
1%
b1 B
#3790000
0*
0%
#3795000
1*
1%
b10 B
#3800000
0*
0%
#3805000
1*
1%
b11 B
#3810000
0*
0%
#3815000
1*
1%
b100 B
19
1:
#3820000
0*
0%
#3825000
1*
0"
1%
0=
b110 @
b0 B
09
0:
#3830000
0*
0%
#3835000
1*
1%
b1 B
#3840000
0*
0%
#3845000
1*
1%
b10 B
#3850000
0*
0%
#3855000
1*
1%
b11 B
#3860000
0*
0%
#3865000
1*
1%
b100 B
19
1;
#3870000
0*
0%
#3875000
1*
1"
1%
1=
b0 B
09
0;
#3880000
0*
0%
#3885000
1*
1%
b1 B
#3890000
0*
0%
#3895000
1*
1%
b10 B
#3900000
0*
0%
#3905000
1*
1%
b11 B
#3910000
0*
0%
#3915000
1*
1%
b100 B
19
1:
#3920000
0*
0%
#3925000
1*
0"
1%
0=
b111 @
b0 B
09
0:
#3930000
0*
0%
#3935000
1*
1%
b1 B
#3940000
0*
0%
#3945000
1*
1%
b10 B
#3950000
0*
0%
#3955000
1*
1%
b11 B
#3960000
0*
0%
#3965000
1*
1%
b100 B
19
1;
#3970000
0*
0%
#3975000
1*
1"
1%
1=
b0 B
09
0;
#3980000
0*
0%
#3985000
1*
1%
b1 B
#3990000
0*
0%
#3995000
1*
1%
b10 B
#4000000
0*
0%
#4005000
1*
1%
b11 B
#4010000
0*
0%
#4015000
1*
1%
b100 B
19
1:
#4020000
0*
0%
#4025000
1*
0"
1%
0=
b1000 @
b0 B
09
0:
#4030000
0*
0%
#4035000
1*
1%
b1 B
#4040000
0*
0%
#4045000
1*
1%
b10 B
#4050000
0*
0%
#4055000
1*
1%
b11 B
#4060000
0*
0%
#4065000
1*
1%
b100 B
19
1;
#4070000
0*
0%
#4075000
1*
1"
1%
1=
b0 B
09
0;
#4080000
0*
0%
#4085000
1*
1%
b1 B
#4090000
0*
0%
#4095000
1*
1%
b10 B
#4100000
0*
0%
#4105000
1*
1%
b11 B
#4110000
0*
0%
#4115000
1*
1%
b100 B
19
1:
#4120000
0*
0%
#4125000
1*
0"
1#
1$
1%
0=
1>
1?
b1001 @
b0 B
0C
09
0:
#4130000
0*
0%
#4135000
1*
0$
1%
0?
